README.rst
setup.py
yoton/__init__.py
yoton/connections.py
yoton.egg-info/PKG-INFO
yoton.egg-info/SOURCES.txt
yoton.egg-info/dependency_links.txt
yoton.egg-info/requires.txt
yoton.egg-info/top_level.txt