Metadata-Version: 1.1
Name: yoton
Version: 0.1.0
Summary: Cache decorator to make applying cache less pain
Home-page: https://github.com/ivannotes/yoton
Author: Ivan Lee
Author-email: miracle.ivanlee@gmail.com
License: MIT
Platform: any
Classifier: Intended Audience :: Developers
Classifier: License :: OSI Approved :: MIT License
Classifier: Operating System :: OS Independent
Classifier: Programming Language :: Python
Classifier: Programming Language :: Python :: 2.7
Classifier: Topic :: Software Development :: Libraries :: Python Modules
